odoo9_addon_l10n_fr_tax_sale_ttc-9.0.1.0.0-py2.7-nspkg.pth
odoo_addons/l10n_fr_tax_sale_ttc/__openerp__.py
odoo_addons/l10n_fr_tax_sale_ttc/__init__.py
odoo_addons/l10n_fr_tax_sale_ttc/README.rst
odoo_addons/l10n_fr_tax_sale_ttc/fr_tax.xml
odoo9_addon_l10n_fr_tax_sale_ttc-9.0.1.0.0.dist-info/top_level.txt
odoo9_addon_l10n_fr_tax_sale_ttc-9.0.1.0.0.dist-info/WHEEL
odoo9_addon_l10n_fr_tax_sale_ttc-9.0.1.0.0.dist-info/RECORD
odoo9_addon_l10n_fr_tax_sale_ttc-9.0.1.0.0.dist-info/metadata.json
odoo9_addon_l10n_fr_tax_sale_ttc-9.0.1.0.0.dist-info/DESCRIPTION.rst
odoo9_addon_l10n_fr_tax_sale_ttc-9.0.1.0.0.dist-info/METADATA
odoo9_addon_l10n_fr_tax_sale_ttc-9.0.1.0.0.dist-info/namespace_packages.txt
