Metadata-Version: 2.0
Name: odoo9-addon-l10n-fr-tax-sale-ttc
Version: 9.0.1.0.0
Summary: Adds Sale Tax TTC (all rates)
Home-page: http://www.akretion.com
Author: UNKNOWN
Author-email: UNKNOWN
License: AGPL-3
Platform: UNKNOWN
Requires-Dist: odoo (<9.1a,>=9.0a)
Classifier: Programming Language :: Python :: 2.7
Classifier: Framework :: Odoo
Classifier: License :: OSI Approved :: GNU Affero General Public License v3
